{"type": "Feature", "id": 12513775, "properties": {"woe:id": 12513775, "woe:parent_id": 1968069, "woe:name": "Ben Gurion Airport", "woe:placetype": 14, "woe:placetype_name": "Airport", "woe:lang": "ENG", "iso:country": "IL", "meta:provider": ["geoplanet:7.3.1", "geoplanet:7.3.2", "geoplanet:7.4.0", "geoplanet:7.4.1", "geoplanet:7.5.1", "geoplanet:7.5.2", "geoplanet:7.6.0", "geoplanet:7.8.1", "geoplanet:7.9.0", "geoplanet:7.10.0", "geoplanet:8.0.0", "woeplanet:8.0.0"], "meta:indexed": "2020-08-20T20:29:16.354490", "woe:alias_ENG_V": ["TLV Airport", "TLV"], "meta:updated": "2020-08-22T01:57:50.654562", "woe:hierarchy": {"continent": 24865671, "country": 23424852, "town": 0, "planet": 1, "county": 0, "suburb": 0, "state": 2345792, "region": 0, "localadmin": 0}, "woe:timezone_id": 28350832, "woe:hash": "sv8y1ge39j6k", "woe:centroid": [34.886101, 32.0117], "geom:latitude": 32.0117, "geom:longitude": 34.886101, "geom:hash": "sv8y1ge39j6k", "woe:latitude": 32.0117, "geom:centroid": [34.886101, 32.0117], "woe:longitude": 34.886101, "woe:repo": "woeplanet-airport-il"}, "geometry": {"coordinates": [34.886101, 32.0117], "type": "Point"}}